hello/__init__.py
hello/hello.py
hellojollytest20230831-0.0.3.dist-info/LICENSE
hellojollytest20230831-0.0.3.dist-info/METADATA
hellojollytest20230831-0.0.3.dist-info/WHEEL
hellojollytest20230831-0.0.3.dist-info/top_level.txt
hellojollytest20230831-0.0.3.dist-info/RECORD
